[{"model": "goods_app.specifications", "pk": 1, "fields": {"value": "Rus", "product": 29, "current_specification": 1}}, {"model": "goods_app.specifications", "pk": 2, "fields": {"value": "Rus", "product": 16, "current_specification": 1}}, {"model": "goods_app.specifications", "pk": 3, "fields": {"value": "black", "product": 16, "current_specification": 2}}, {"model": "goods_app.specifications", "pk": 4, "fields": {"value": "17x24", "product": 16, "current_specification": 3}}, {"model": "goods_app.specifications", "pk": 5, "fields": {"value": "2h", "product": 16, "current_specification": 4}}, {"model": "goods_app.specifications", "pk": 6, "fields": {"value": "Rus", "product": 17, "current_specification": 1}}, {"model": "goods_app.specifications", "pk": 7, "fields": {"value": "white", "product": 17, "current_specification": 2}}, {"model": "goods_app.specifications", "pk": 8, "fields": {"value": "14", "product": 17, "current_specification": 5}}, {"model": "goods_app.specifications", "pk": 9, "fields": {"value": "Rus", "product": 18, "current_specification": 1}}, {"model": "goods_app.specifications", "pk": 10, "fields": {"value": "black", "product": 18, "current_specification": 2}}, {"model": "goods_app.specifications", "pk": 11, "fields": {"value": "3h", "product": 18, "current_specification": 4}}, {"model": "goods_app.specifications", "pk": 12, "fields": {"value": "17x25", "product": 18, "current_specification": 3}}, {"model": "goods_app.specifications", "pk": 13, "fields": {"value": "Rus", "product": 19, "current_specification": 1}}, {"model": "goods_app.specifications", "pk": 14, "fields": {"value": "27x45", "product": 19, "current_specification": 3}}, {"model": "goods_app.specifications", "pk": 15, "fields": {"value": "11", "product": 19, "current_specification": 5}}, {"model": "goods_app.specifications", "pk": 16, "fields": {"value": "Rus", "product": 20, "current_specification": 1}}, {"model": "goods_app.specifications", "pk": 17, "fields": {"value": "9x32", "product": 20, "current_specification": 3}}, {"model": "goods_app.specifications", "pk": 18, "fields": {"value": "white", "product": 20, "current_specification": 2}}, {"model": "goods_app.specifications", "pk": 19, "fields": {"value": "1h", "product": 20, "current_specification": 4}}, {"model": "goods_app.specifications", "pk": 20, "fields": {"value": "Rus", "product": 21, "current_specification": 1}}, {"model": "goods_app.specifications", "pk": 21, "fields": {"value": "black", "product": 21, "current_specification": 2}}, {"model": "goods_app.specifications", "pk": 22, "fields": {"value": "HD", "product": 21, "current_specification": 6}}, {"model": "goods_app.specifications", "pk": 23, "fields": {"value": "5", "product": 21, "current_specification": 5}}, {"model": "goods_app.specifications", "pk": 24, "fields": {"value": "Rus", "product": 22, "current_specification": 1}}, {"model": "goods_app.specifications", "pk": 25, "fields": {"value": "34", "product": 22, "current_specification": 5}}, {"model": "goods_app.specifications", "pk": 26, "fields": {"value": "white", "product": 22, "current_specification": 2}}, {"model": "goods_app.specifications", "pk": 27, "fields": {"value": "Rus", "product": 23, "current_specification": 1}}, {"model": "goods_app.specifications", "pk": 28, "fields": {"value": "2h", "product": 23, "current_specification": 4}}, {"model": "goods_app.specifications", "pk": 29, "fields": {"value": "white", "product": 23, "current_specification": 2}}, {"model": "goods_app.specifications", "pk": 30, "fields": {"value": "Rus", "product": 24, "current_specification": 1}}, {"model": "goods_app.specifications", "pk": 31, "fields": {"value": "12x41", "product": 24, "current_specification": 3}}, {"model": "goods_app.specifications", "pk": 32, "fields": {"value": "2h", "product": 24, "current_specification": 4}}, {"model": "goods_app.specifications", "pk": 33, "fields": {"value": "Rus", "product": 25, "current_specification": 1}}, {"model": "goods_app.specifications", "pk": 34, "fields": {"value": "black", "product": 25, "current_specification": 2}}, {"model": "goods_app.specifications", "pk": 35, "fields": {"value": "7", "product": 25, "current_specification": 5}}, {"model": "goods_app.specifications", "pk": 36, "fields": {"value": "Rus", "product": 26, "current_specification": 1}}, {"model": "goods_app.specifications", "pk": 37, "fields": {"value": "white", "product": 26, "current_specification": 2}}, {"model": "goods_app.specifications", "pk": 38, "fields": {"value": "7x23", "product": 26, "current_specification": 3}}, {"model": "goods_app.specifications", "pk": 39, "fields": {"value": "Rus", "product": 27, "current_specification": 1}}, {"model": "goods_app.specifications", "pk": 40, "fields": {"value": "white", "product": 27, "current_specification": 2}}, {"model": "goods_app.specifications", "pk": 41, "fields": {"value": "13", "product": 27, "current_specification": 5}}, {"model": "goods_app.specifications", "pk": 42, "fields": {"value": "Rus", "product": 28, "current_specification": 1}}, {"model": "goods_app.specifications", "pk": 43, "fields": {"value": "white", "product": 28, "current_specification": 2}}, {"model": "goods_app.specifications", "pk": 44, "fields": {"value": "34", "product": 28, "current_specification": 5}}, {"model": "goods_app.specifications", "pk": 45, "fields": {"value": "34x11", "product": 28, "current_specification": 3}}, {"model": "goods_app.specifications", "pk": 46, "fields": {"value": "Rus", "product": 27, "current_specification": 1}}, {"model": "goods_app.specifications", "pk": 47, "fields": {"value": "white", "product": 27, "current_specification": 2}}, {"model": "goods_app.specifications", "pk": 48, "fields": {"value": "16x20", "product": 27, "current_specification": 3}}, {"model": "goods_app.specifications", "pk": 49, "fields": {"value": "14", "product": 27, "current_specification": 5}}, {"model": "goods_app.specifications", "pk": 50, "fields": {"value": "Rus", "product": 28, "current_specification": 1}}, {"model": "goods_app.specifications", "pk": 51, "fields": {"value": "black", "product": 28, "current_specification": 2}}, {"model": "goods_app.specifications", "pk": 52, "fields": {"value": "11x3", "product": 28, "current_specification": 3}}, {"model": "goods_app.specifications", "pk": 53, "fields": {"value": "12", "product": 28, "current_specification": 5}}, {"model": "goods_app.specifications", "pk": 54, "fields": {"value": "white", "product": 29, "current_specification": 2}}, {"model": "goods_app.specifications", "pk": 55, "fields": {"value": "2h", "product": 29, "current_specification": 4}}, {"model": "goods_app.specifications", "pk": 56, "fields": {"value": "Rus", "product": 30, "current_specification": 1}}, {"model": "goods_app.specifications", "pk": 57, "fields": {"value": "15x27", "product": 30, "current_specification": 3}}, {"model": "goods_app.specifications", "pk": 58, "fields": {"value": "3h", "product": 30, "current_specification": 4}}, {"model": "goods_app.specifications", "pk": 59, "fields": {"value": "14", "product": 30, "current_specification": 5}}, {"model": "goods_app.specifications", "pk": 60, "fields": {"value": "Rus", "product": 31, "current_specification": 1}}, {"model": "goods_app.specifications", "pk": 61, "fields": {"value": "43", "product": 31, "current_specification": 5}}, {"model": "goods_app.specifications", "pk": 62, "fields": {"value": "34x143", "product": 31, "current_specification": 3}}, {"model": "goods_app.specifications", "pk": 63, "fields": {"value": "Rus", "product": 32, "current_specification": 1}}, {"model": "goods_app.specifications", "pk": 64, "fields": {"value": "16", "product": 32, "current_specification": 5}}, {"model": "goods_app.specifications", "pk": 65, "fields": {"value": "39x56", "product": 32, "current_specification": 3}}, {"model": "goods_app.specifications", "pk": 66, "fields": {"value": "Rus", "product": 33, "current_specification": 1}}, {"model": "goods_app.specifications", "pk": 67, "fields": {"value": "white", "product": 33, "current_specification": 2}}, {"model": "goods_app.specifications", "pk": 68, "fields": {"value": "71x22", "product": 33, "current_specification": 3}}, {"model": "goods_app.specifications", "pk": 69, "fields": {"value": "57", "product": 33, "current_specification": 5}}]